example/__init__.py
example/main.py
pyrpgmaker/__init__.py
pyrpgmaker/implementation/__init__.py
pyrpgmaker/implementation/main.py
pyrpgmaker/interface/__init__.py
pyrpgmaker/interface/gui.py
pyrpgmaker/interface/layer.py
pyrpgmaker/interface/scene.py
pyrpgmaker-0.1.1.dist-info/licenses/LICENSE
pyrpgmaker-0.1.1.dist-info/METADATA
pyrpgmaker-0.1.1.dist-info/WHEEL
pyrpgmaker-0.1.1.dist-info/top_level.txt
pyrpgmaker-0.1.1.dist-info/RECORD
