Metadata-Version: 2.4
Name: pyrpgmaker
Version: 0.1.1
Summary: A Python RPG Maker
Home-page: https://github.com/yx-z/pyrpgmaker
Author: yx-z
Author-email: yx-z@outlook.com
Classifier: Programming Language :: Python :: 3
Classifier: License :: OSI Approved :: MIT License
Classifier: Operating System :: OS Independent
Requires-Python: >=3.13
License-File: LICENSE
Requires-Dist: pygame
Requires-Dist: Pillow
Dynamic: author
Dynamic: author-email
Dynamic: classifier
Dynamic: description
Dynamic: description-content-type
Dynamic: home-page
Dynamic: license-file
Dynamic: requires-dist
Dynamic: requires-python
Dynamic: summary
